limitry/__init__.py
limitry/client/__init__.py
limitry/client/client.py
limitry/client/config.py
limitry/client/exceptions.py
limitry/client/resources/__init__.py
limitry/client/resources/customers.py
limitry/client/resources/events.py
limitry/client/resources/project.py
limitry/client/resources/quota_alerts.py
limitry/client/resources/quotas.py
limitry/client/resources/rate_limits.py
limitry/client/resources/track.py
limitry/client/resources/usage.py
limitry/client/tests/__init__.py
limitry/client/tests/test_client.py
limitry/client/tests/test_exceptions.py
limitry/client/types.py
limitry/client/utils/__init__.py
limitry/client/utils/pagination.py
limitry/sdk/__init__.py
limitry-0.4.0.dist-info/METADATA
limitry-0.4.0.dist-info/WHEEL
limitry-0.4.0.dist-info/entry_points.txt
limitry-0.4.0.dist-info/licenses/LICENSE
limitry-0.4.0.dist-info/RECORD
