Metadata-Version: 2.4
Name: limitry
Version: 0.4.0
Summary: Limitry Python SDK
License: MIT
License-File: LICENSE
Keywords: limitry,sdk,python,api,client
Author: Limitry
Author-email: support@limitry.com
Requires-Python: >=3.10,<4.0
Classifier: License :: OSI Approved :: MIT License
Classifier: Programming Language :: Python :: 3
Classifier: Programming Language :: Python :: 3.10
Classifier: Programming Language :: Python :: 3.11
Classifier: Programming Language :: Python :: 3.12
Classifier: Programming Language :: Python :: 3.13
Classifier: Programming Language :: Python :: 3.14
Requires-Dist: httpx (>=0.28.1,<0.29.0)
Requires-Dist: pydantic (>=2.9.0,<3.0.0)
Project-URL: Homepage, https://github.com/limitry/limitry-python
Project-URL: Repository, https://github.com/limitry/limitry-python
